trialhub/__init__.py
trialhub/azure_storage.py
trialhub/config.json
trialhub/helper.py
trialhub/mongodb.py
trialhub/open_ai.py
trialhub/pubmed_download.py
trialhub/pubmed_entrez.py
trialhub/vector_db.py
trialhub-0.0.11.dist-info/LICENSE.txt
trialhub-0.0.11.dist-info/METADATA
trialhub-0.0.11.dist-info/WHEEL
trialhub-0.0.11.dist-info/top_level.txt
trialhub-0.0.11.dist-info/RECORD
